tikzplotlib/__about__.py
tikzplotlib/__init__.py
tikzplotlib/_axes.py
tikzplotlib/_cleanfigure.py
tikzplotlib/_color.py
tikzplotlib/_files.py
tikzplotlib/_hatches.py
tikzplotlib/_image.py
tikzplotlib/_legend.py
tikzplotlib/_line2d.py
tikzplotlib/_markers.py
tikzplotlib/_patch.py
tikzplotlib/_path.py
tikzplotlib/_quadmesh.py
tikzplotlib/_save.py
tikzplotlib/_text.py
tikzplotlib/_util.py
tikzplotlib_patched-0.10.1.post13.dist-info/LICENSE
tikzplotlib_patched-0.10.1.post13.dist-info/WHEEL
tikzplotlib_patched-0.10.1.post13.dist-info/METADATA
tikzplotlib_patched-0.10.1.post13.dist-info/RECORD
